mlflow_extra/__init__.py
mlflow_extra/common.py
mlflow_extra/filter.py
mlflow_extra/merge.py
mlflow_extra/metadata.py
mlflow_extra/uri.py
mlflow_extra/version.py
mlflow_extra-2023.7.dist-info/METADATA
mlflow_extra-2023.7.dist-info/WHEEL
mlflow_extra-2023.7.dist-info/entry_points.txt
mlflow_extra-2023.7.dist-info/licenses/LICENSE.txt
mlflow_extra-2023.7.dist-info/RECORD
