Metadata-Version: 2.1
Name: mlflow-extra
Version: 2023.7
Summary: Utilities for MLflow
Project-URL: homepage, https://gitlab.inria.fr/jrye/mlflow-extra
Project-URL: repository, https://gitlab.inria.fr/jrye/mlflow-extra.git
Project-URL: documentation, https://jrye.gitlabpages.inria.fr/mlflow-extra
Project-URL: issues, https://gitlab.inria.fr/jrye/mlflow-extra/-/issues
Author-email: Jan-Michael Rye <jan-michael.rye@inria.fr>
License: MIT License
License-File: LICENSE.txt
Classifier: Operating System :: OS Independent
Classifier: Programming Language :: Python :: 3
Requires-Python: >=3.6
Requires-Dist: mlflow
Requires-Dist: pyyaml
